{"intension": "Promote wedding organizer services by creating a business card with a professional and elegant design. Include contact information such as name, phone number, email, and website. ", "globalcaption": "The image features a green background with a white border. The border is adorned with white flowers, creating a visually appealing design. The main focus of the image is a business card for a wedding organizer, which is placed on top of the green background. The card is white and has a professional appearance, making it an attractive choice for a wedding organizer.", "canvas_width": 1080, "canvas_height": 1080, "category": "Business Card European", "keywords": "celebration, ceremony, marriage, wedding, tb, service, gray, business card, organizer, elegant, flowers, frame", "layers": {"bglayer": {"bgcaption": "The image is a close-up of a green background, which appears to be a wall or a piece of fabric. The green color is dominant, covering the entire frame. There are no other objects or details visible in the image, making it a simple and monochromatic composition"}, "objlayer": {"flag": "<flag-1>", "objcaption": "The image features a white background with two flower designs on it. The first flower design is located on the left side of the image, while the second flower design is on the right side. Both flowers are white and green in color, and they appear to be decorative and artistic. The overall composition of the image is simple and clean, with the flowers being the main focus"}, "textlayer": {"heading": [{"text": "Business Name", "font": "Cinzel Decorative", "font_size": 75.26, "text_align": "center", "capitalize": "false", "angle": 0.0, "letter_bold": 1, "letter_spacing": 0.0, "width": 729.84375, "height": 75.9375, "left": 172.96875, "top": 497.8125, "opacity": 255, "color": [255, 255, 255]}], "subheading": [{"text": "Wedding Organizer", "font": "Cinzel Decorative", "font_size": 49.519999999999996, "text_align": "center", "capitalize": "false", "angle": 0.0, "letter_bold": 0, "letter_spacing": 0.0, "width": 729.84375, "height": 46.40625, "left": 172.96875, "top": 569.53125, "opacity": 255, "color": [255, 255, 255]}], "body": [{"text": "Name Surname", "font": "Cinzel Decorative", "font_size": 23.78, "text_align": "center", "capitalize": "false", "angle": 0.0, "letter_bold": 1, "letter_spacing": 0.0, "width": 729.84375, "height": 21.09375, "left": 172.96875, "top": 194.0625, "opacity": 255, "color": [255, 255, 255]}, {"text": "+123-456-7890", "font": "Montserrat", "font_size": 27.74, "text_align": "center", "capitalize": "false", "angle": 0.0, "letter_bold": 0, "letter_spacing": 0.0, "width": 729.84375, "height": 25.3125, "left": 172.96875, "top": 721.40625, "opacity": 255, "color": [255, 255, 255]}, {"text": "yourmail@somemail.com", "font": "Montserrat", "font_size": 27.74, "text_align": "center", "capitalize": "false", "angle": 0.0, "letter_bold": 0, "letter_spacing": 0.0, "width": 729.84375, "height": 25.3125, "left": 172.96875, "top": 721.40625, "opacity": 255, "color": [255, 255, 255]}, {"text": "www", "font": "Montserrat", "font_size": 27.74, "text_align": "center", "capitalize": "false", "angle": 0.0, "letter_bold": 0, "letter_spacing": 0.0, "width": 729.84375, "height": 25.3125, "left": 172.96875, "top": 856.40625, "opacity": 255, "color": [255, 255, 255]}]}}}