{"intension": "Create a romantic Valentine's Day card with a heartfelt message and playful heart illustrations.", "globalcaption": "The image features a pink background with a heart-shaped message written in white text. The message reads,", "canvas_width": 1080, "canvas_height": 1080, "category": "Instagram Post", "keywords": "love, romantic, day, heart, romance, celebration, holiday, february, happy, card, valentines, greeting, pink, instagram, post, insta, ig, tb", "layers": {"bglayer": {"bgcaption": "The image features a pink background with a series of hearts scattered across it. The hearts come in various sizes and are positioned at different angles, creating a visually appealing pattern. The hearts are spread out across the entire background, with some closer to the edges and others more centrally located. The overall scene is a playful and cheerful display of hearts"}, "objlayer": {"flag": "<flag-0>", "objcaption": ""}, "textlayer": {"heading": [{"text": "", "font": "Playlist", "font_size": 200.0, "text_align": "center", "capitalize": "false", "angle": 0.0, "letter_bold": 0, "letter_spacing": 0.0, "width": 172.96875, "height": 215.15625, "left": 0.0, "top": 0.0, "opacity": 255, "color": [255, 255, 255]}], "subheading": [{"text": "Every day I spend with you", "font": "Pompiere", "font_size": 69.32, "text_align": "center", "capitalize": "false", "angle": 0.0, "letter_bold": 0, "letter_spacing": 0.0, "width": 628.59375, "height": 139.21875, "left": 223.59375, "top": 354.375, "opacity": 255, "color": [255, 255, 255]}, {"text": "is the next best day of my life", "font": "Pompiere", "font_size": 69.32, "text_align": "center", "capitalize": "false", "angle": 0.0, "letter_bold": 0, "letter_spacing": 0.0, "width": 628.59375, "height": 67.5, "left": 223.59375, "top": 582.1875, "opacity": 255, "color": [255, 255, 255]}, {"text": "Happy Valentine\\u2019s", "font": "Playlist", "font_size": 69.32, "text_align": "center", "capitalize": "false", "angle": 0.0, "letter_bold": 0, "letter_spacing": 0.0, "width": 628.59375, "height": 67.5, "left": 223.59375, "top": 586.40625, "opacity": 255, "color": [255, 255, 255]}], "body": [{"text": "", "font": "Playlist", "font_size": 63.38, "text_align": "center", "capitalize": "false", "angle": 0.0, "letter_bold": 0, "letter_spacing": 0.0, "width": 42.1875, "height": 63.28125, "left": 101.25, "top": 805.78125, "opacity": 255, "color": [207, 7, 39]}]}}}